main.py
validate_secrets-0.0.0.post0.dist-info/METADATA
validate_secrets-0.0.0.post0.dist-info/WHEEL
validate_secrets-0.0.0.post0.dist-info/top_level.txt
validate_secrets-0.0.0.post0.dist-info/RECORD
