Metadata-Version: 2.4
Name: validate-secrets
Version: 0.0.0.post0
Summary: Coming soon!
Requires-Python: >=3.11
